noseOfYeti/__init__.py
noseOfYeti/version.py
noseOfYeti/black/Grammar.noy.txt
noseOfYeti/plugins/__init__.py
noseOfYeti/plugins/black_compat.py
noseOfYeti/plugins/mypy.py
noseOfYeti/plugins/nosetests.py
noseOfYeti/plugins/pylama.py
noseOfYeti/plugins/pyls.py
noseOfYeti/plugins/pytest.py
noseOfYeti/tokeniser/__init__.py
noseOfYeti/tokeniser/chooser.py
noseOfYeti/tokeniser/containers.py
noseOfYeti/tokeniser/spec_codec.py
noseOfYeti/tokeniser/support.py
noseOfYeti/tokeniser/tokeniser.py
noseOfYeti/tokeniser/tokens.py
noseOfYeti/tokeniser/tracker.py
noy_black.pth
noseofyeti-2.4.9.dist-info/METADATA
noseofyeti-2.4.9.dist-info/WHEEL
noseofyeti-2.4.9.dist-info/entry_points.txt
noseofyeti-2.4.9.dist-info/licenses/LICENSE
noseofyeti-2.4.9.dist-info/RECORD
