Metadata-Version: 2.3
Name: noseOfYeti
Version: 2.4.9
Summary: A custom python codec that provides an RSpec style dsl for python
Project-URL: Homepage, https://github.com/delfick/nose-of-yeti
Author-email: Stephen Moore <stephen@delfick.com>
License-Expression: MIT
License-File: LICENSE
Keywords: bdd,rspec,spec
Classifier: Intended Audience :: Developers
Classifier: Programming Language :: Python
Classifier: Topic :: Software Development :: Documentation
Classifier: Topic :: Software Development :: Testing
Requires-Python: >=3.8
Provides-Extra: black
Requires-Dist: black==24.2.0; extra == 'black'
Requires-Dist: importlib-resources==5.10.0; extra == 'black'
Provides-Extra: tests
Requires-Dist: alt-pytest-asyncio==0.6.0; extra == 'tests'
Requires-Dist: pytest-helpers-namespace==2021.4.29; extra == 'tests'
Requires-Dist: pytest>=7.0.1; extra == 'tests'
